mosaik_csv.py
mosaik.CSV_SemVer-1.0.4rc20211006105348.dist-info/AUTHORS.txt
mosaik.CSV_SemVer-1.0.4rc20211006105348.dist-info/LICENSE.txt
mosaik.CSV_SemVer-1.0.4rc20211006105348.dist-info/METADATA
mosaik.CSV_SemVer-1.0.4rc20211006105348.dist-info/WHEEL
mosaik.CSV_SemVer-1.0.4rc20211006105348.dist-info/entry_points.txt
mosaik.CSV_SemVer-1.0.4rc20211006105348.dist-info/top_level.txt
mosaik.CSV_SemVer-1.0.4rc20211006105348.dist-info/RECORD
