Metadata-Version: 2.1
Name: mosaik.CSV-SemVer
Version: 1.0.4rc20211006105348
Summary: Presents CSV datasets to mosaik as models.
Home-page: https://bitbucket.org/mosaik/mosaik-csv
Author: Stefan Scherfke
Author-email: mosaik@offis.de
Maintainer: Bengt Lüers
Maintainer-email: bengt.lueers@gmail.com
License: UNKNOWN
Platform: UNKNOWN
Classifier: Development Status :: 5 - Production/Stable
Classifier: Environment :: Console
Classifier: Intended Audience :: Science/Research
Classifier: License :: OSI Approved :: GNU Lesser General Public License v2 (LGPLv2)
Classifier: Natural Language :: English
Classifier: Operating System :: OS Independent
Classifier: Programming Language :: Python
Classifier: Programming Language :: Python :: 3
Classifier: Programming Language :: Python :: 3.7
Classifier: Programming Language :: Python :: 3.8
Classifier: Programming Language :: Python :: 3.9
Classifier: Topic :: Scientific/Engineering
Requires-Dist: arrow (>=0.9.0)
Requires-Dist: mosaik.API-SemVer (>=2.4.2rc20201202042235)
